setup.cfg
setup.py
bin/__init__.py
bin/opensubz.py
opensubtitles/__init__.py
opensubtitles/opensubtitles.py
opensubtitles/settings.py
opensubtitles/utils.py
opensubz/__init__.py
opensubz/config.py
opensubz/context_menu.py
opensubz/core.py
opensubz.egg-info/PKG-INFO
opensubz.egg-info/SOURCES.txt
opensubz.egg-info/dependency_links.txt
opensubz.egg-info/entry_points.txt
opensubz.egg-info/requires.txt
opensubz.egg-info/top_level.txt