Metadata-Version: 1.1
Name: opensubz
Version: 0.2.1
Summary: Two-click subtitle downloader script
Home-page: https://github.com/danielfsousa/opensubz
Author: Daniel Sousa
Author-email: sousa.dfs@gmail.com
License: MIT
Download-URL: https://github.com/danielfsousa/opensubz/archive/0.2.1.tar.gz
Keywords: script download subtitles opensubtitles
Platform: UNKNOWN
Classifier: Development Status :: 5 - Production/Stable
Classifier: Intended Audience :: End Users/Desktop
Classifier: Topic :: Multimedia
Classifier: Environment :: Win32 (MS Windows)
Classifier: Operating System :: Microsoft :: Windows
Classifier: License :: OSI Approved :: MIT License
Classifier: Programming Language :: Python :: 3
Classifier: Programming Language :: Python :: 3.3
Classifier: Programming Language :: Python :: 3.4
Classifier: Programming Language :: Python :: 3.5
Classifier: Programming Language :: Python :: 3.6
